ucloudauth
