Metadata-Version: 1.1
Name: requests-ucloud
Version: 0.3.0
Summary: authentication for ucloud service
Home-page: http://github.com/skylothar/requests-ucloud
Author: SkyLothar
Author-email: allothar@gmail.com
License: Apache 2.0
Platform: UNKNOWN
Classifier: Development Status :: 4 - Beta
Classifier: Intended Audience :: Developers
Classifier: Natural Language :: English
Classifier: License :: OSI Approved :: Apache Software License
Classifier: Programming Language :: Python
Classifier: Programming Language :: Python :: 2.7
Classifier: Programming Language :: Python :: 3
Classifier: Programming Language :: Python :: 3.3
Classifier: Programming Language :: Python :: 3.4
